{
  "asset": "XRP",
  "timeframe": "1d",
  "computed_at": "2026-06-04T17:01:15.212444+00:00",
  "last_close": 1.1686,
  "pred_len": 24,
  "forecast_start": "2026-06-05 00:00:00+00:00",
  "forecast_end": "2026-06-28 00:00:00+00:00",
  "metrics": {
    "n_paths": 20,
    "mean_final_price": 1.793456,
    "std_final_price": 0.264079,
    "sharpness": 0.147246,
    "expected_return": 0.534705,
    "std_return": 0.225979,
    "signal_sharpe": 2.3662,
    "direction_prob": 1.0,
    "upside": 0.534705,
    "downside": 0.0,
    "risk_reward": NaN,
    "best_case_p95": 0.966982,
    "worst_case_p5": 0.18607,
    "conviction": 0.0
  },
  "signals": {
    "entry": "neutral",
    "entry_reason": "high dispersion across paths (sharpness=0.147); conviction too low (0.00)",
    "stay_long": "stay_long",
    "stay_long_reason": "forecast still supportive: expected return 53.47%, 100% bullish paths",
    "stay_short": "exit_short",
    "stay_short_reason": "model now expects positive return (53.47%) \u2014 close short"
  }
}