{
  "asset": "XRP",
  "timeframe": "4h",
  "computed_at": "2026-06-09T16:38:11.060674+00:00",
  "last_close": 1.129,
  "pred_len": 24,
  "forecast_start": "2026-06-09 20:00:00+00:00",
  "forecast_end": "2026-06-13 16:00:00+00:00",
  "metrics": {
    "n_paths": 20,
    "mean_final_price": 1.173324,
    "std_final_price": 0.034022,
    "sharpness": 0.028996,
    "expected_return": 0.039259,
    "std_return": 0.030135,
    "signal_sharpe": 1.3028,
    "direction_prob": 0.9,
    "upside": 0.046714,
    "downside": -0.02783,
    "risk_reward": 1.6785,
    "best_case_p95": 0.071209,
    "worst_case_p5": -0.004723,
    "conviction": 0.568
  },
  "signals": {
    "entry": "long",
    "entry_reason": "90% of paths are bullish, expected return +3.93%, conviction 0.57",
    "stay_long": "stay_long",
    "stay_long_reason": "forecast still supportive: expected return 3.93%, 90% bullish paths",
    "stay_short": "exit_short",
    "stay_short_reason": "model now expects positive return (3.93%) \u2014 close short"
  }
}